wmctrl.py
wmctrl_python3-0.3.dist-info/METADATA
wmctrl_python3-0.3.dist-info/WHEEL
wmctrl_python3-0.3.dist-info/top_level.txt
wmctrl_python3-0.3.dist-info/RECORD
