Metadata-Version: 2.1
Name: wmctrl-python3
Version: 0.3
Summary: A tool to programmatically control windows inside X
Home-page: http://bitbucket.org/antocuni/wmctrl
Author: Antonio Cuni
Author-email: anto.cuni@gmail.com
License: BSD
Platform: UNKNOWN
